topsis_mukul_102097016.py
topsis_mukul_102097016-0.0.1.dist-info/LICENSE
topsis_mukul_102097016-0.0.1.dist-info/METADATA
topsis_mukul_102097016-0.0.1.dist-info/WHEEL
topsis_mukul_102097016-0.0.1.dist-info/top_level.txt
topsis_mukul_102097016-0.0.1.dist-info/RECORD
