Metadata-Version: 2.1
Name: topsis-mukul-102097016
Version: 0.0.1
Summary: Topsis package by Mukul Tayal-102097016-CSE4
Home-page: UNKNOWN
Author: Bhuvnesh Jindal
License: UNKNOWN
Keywords: mukul tayal,tiet,topsis
Platform: UNKNOWN
Classifier: Programming Language :: Python :: 3
Classifier: License :: OSI Approved :: MIT License
Classifier: Operating System :: OS Independent
Requires-Python: >=3.6
Requires-Dist: pandas
